querytools
