Metadata-Version: 2.1
Name: dj-querytools
Version: 0.2.3
Summary: Some utility functions to perform complex queries with the Django ORM
Home-page: https://gitlab.com/SchoolOrchestration/libs/dj-querytools
Author: AppointmentGuru
Author-email: tech@appointmentguru.co
License: UNKNOWN
Platform: UNKNOWN
Classifier: Programming Language :: Python :: 3
Classifier: Operating System :: OS Independent
